{
    "crs": {
        "properties": {
            "name": "urn:ogc:def:crs:OGC:1.3:CRS84"
        },
        "type": "name"
    },
    "features": [
        {
            "geometry": {
                "coordinates": [
                    -122.2612529999318,
                    37.7641499997259
                ],
                "type": "Point"
            },
            "properties": {
                "AIM_id": "0",
                "BridgeClass": 201,
                "BridgeHazusClass": "HWB1",
                "DeckWidth": 905.511811023622,
                "Location": 0,
                "MaxSpanLength": 358.26771653543307,
                "NumOfSpans": 3,
                "R2Dres_MostLikelyCriticalDamageState": 2,
                "R2Dres_MostLikelyDamageState_HWB.GF-1": 2,
                "R2Dres_MostLikelyDamageState_HWB.GS.1-1": 0,
                "R2Dres_MostLikelyDamageState_collapse-0": 0,
                "R2Dres_mean_Collapse": 0,
                "R2Dres_mean_Irreparable": 0,
                "R2Dres_mean_RepairCost": 1.2153999999999998,
                "R2Dres_mean_RepairTime": 132.5,
                "R2Dres_std_Collapse": 0,
                "R2Dres_std_Irreparable": 0,
                "R2Dres_std_RepairCost": 0.4577225572264703,
                "R2Dres_std_RepairTime": 158.25158974419708,
                "Skew": 0,
                "SoilType": "B",
                "StateCode": "06",
                "StructureNumber": "33C0229",
                "YearBuilt": 1958,
                "assetSubtype": "HwyBridge",
                "assetType": "TransportationNetwork",
                "location": {
                    "latitude": 37.7641499997259,
                    "longitude": -122.2612529999318
                },
                "type": "Bridge"
            },
            "type": "Feature"
        }
    ],
    "type": "FeatureCollection"
}
